napari_spacetx_explorer/__init__.py
napari_spacetx_explorer/_csv_io.py
napari_spacetx_explorer/_function.py
napari_spacetx_explorer/_reader.py
napari_spacetx_explorer/_reader_function.py
napari_spacetx_explorer/_tests/__init__py
napari_spacetx_explorer/_tests/test_plugin.py
napari_spacetx_explorer-0.1.8.dist-info/LICENSE
napari_spacetx_explorer-0.1.8.dist-info/METADATA
napari_spacetx_explorer-0.1.8.dist-info/WHEEL
napari_spacetx_explorer-0.1.8.dist-info/entry_points.txt
napari_spacetx_explorer-0.1.8.dist-info/top_level.txt
napari_spacetx_explorer-0.1.8.dist-info/RECORD
