Metadata-Version: 2.1
Name: napari-spacetx-explorer
Version: 0.1.8
Summary: visualizer for spatial omic data
Home-page: https://github.com/sebgoti/napari-spacetx-explorer
Author: Sebastian Gonzalez-Tirado
Author-email: sebastian.gonzalez@embl.de
License: BSD-3
Project-URL: Bug Tracker, https://github.com/sebgoti/napari-spacetx-explorer/issues
Project-URL: Documentation, https://github.com/sebgoti/napari-spacetx-explorer#README.md
Project-URL: Source Code, https://github.com/sebgoti/napari-spacetx-explorer
Project-URL: User Support, https://github.com/sebgoti/napari-spacetx-explorer/issues
Platform: UNKNOWN
Classifier: Development Status :: 3 - Alpha
Classifier: Intended Audience :: Science/Research
Classifier: Framework :: napari
Classifier: Programming Language :: Python
Classifier: Programming Language :: Python :: 3
Classifier: Programming Language :: Python :: 3.7
Classifier: Programming Language :: Python :: 3.8
Classifier: Programming Language :: Python :: 3.9
Classifier: Operating System :: OS Independent
Classifier: License :: OSI Approved :: BSD License
Requires-Python: >=3.7
License-File: LICENSE
Requires-Dist: napari
Requires-Dist: napari-plugin-engine (>=0.1.4)
Requires-Dist: numpy
Requires-Dist: pandas
